Metadata-Version: 2.1
Name: odoo13-addon-l10n_de_skr04_mis_reports
Version: 13.0.1.0.1
Summary: MIS Builder templates for the German P&L and Balance Sheets (SKR04)
Home-page: https://github.com/OCA/l10n-germany
Author: OpenBIG.org,ACSONE SA/NV,Odoo Community Association (OCA)
Author-email: support@odoo-community.org
License: AGPL-3
Classifier: Programming Language :: Python
Classifier: Framework :: Odoo
Classifier: Framework :: Odoo :: 13.0
Classifier: License :: OSI Approved :: GNU Affero General Public License v3
Requires-Python: >=3.5
Requires-Dist: odoo13-addon-mis-builder
Requires-Dist: odoo<13.1dev,>=13.0a
